cryskura/Entry.py
cryskura/Handler.py
cryskura/Server.py
cryskura/__init__.py
cryskura/uPnP.py
cryskura/Icons/cryskura.ico
cryskura/Icons/directory.ico
cryskura/Icons/fileupload.ico
cryskura/Icons/webpage.ico
cryskura/Pages/Cryskura.png
cryskura/Pages/__init__.py
cryskura/Pages/directory.html
cryskura/Pages/error.html
cryskura/Services/APIService.py
cryskura/Services/BaseService.py
cryskura/Services/ErrorService.py
cryskura/Services/FileService.py
cryskura/Services/PageService.py
cryskura/Services/RedirectService.py
cryskura/Services/__init__.py
cryskura-1.0b12.dist-info/licenses/LICENSE
cryskura-1.0b12.dist-info/METADATA
cryskura-1.0b12.dist-info/WHEEL
cryskura-1.0b12.dist-info/entry_points.txt
cryskura-1.0b12.dist-info/top_level.txt
cryskura-1.0b12.dist-info/RECORD
